mcp_server_macos_defaults/__init__.py
mcp_server_macos_defaults/server.py
mseep_mcp_server_macos_defaults-0.1.6.dist-info/METADATA
mseep_mcp_server_macos_defaults-0.1.6.dist-info/WHEEL
mseep_mcp_server_macos_defaults-0.1.6.dist-info/entry_points.txt
mseep_mcp_server_macos_defaults-0.1.6.dist-info/top_level.txt
mseep_mcp_server_macos_defaults-0.1.6.dist-info/RECORD
