Metadata-Version: 2.4
Name: mseep-mcp-server-macos-defaults
Version: 0.1.6
Summary: MCP server for reading/writing macOS defaults (settings)
Author-email: mseep <support@skydeck.ai>
Requires-Python: >=3.13
Requires-Dist: mcp>=1.0.0
